Metadata-Version: 2.1
Name: django-modeltranslation-pr507
Version: 0.14.1
Summary: Translates Django models using a registration approach.
Home-page: https://github.com/deschler/django-modeltranslation
Author: Peter Eschler
Author-email: peschler@gmail.com
Maintainer: Dirk Eschler
Maintainer-email: eschler@gmail.com
License: New BSD
Download-URL: https://github.com/deschler/django-modeltranslation/archive/0.14.1.tar.gz
Platform: UNKNOWN
Classifier: Programming Language :: Python
Classifier: Programming Language :: Python :: 2.7
Classifier: Programming Language :: Python :: 3
Classifier: Programming Language :: Python :: 3.5
Classifier: Programming Language :: Python :: 3.6
Classifier: Programming Language :: Python :: 3.7
Classifier: Operating System :: OS Independent
Classifier: Environment :: Web Environment
Classifier: Intended Audience :: Developers
Classifier: Framework :: Django
Classifier: License :: OSI Approved :: BSD License
Requires-Dist: Django (>=1.11)
Requires-Dist: six
